hello_package/__init__.py
hello_package/hello.py
hello_py_1802-0.1.0.dist-info/LICENSE
hello_py_1802-0.1.0.dist-info/METADATA
hello_py_1802-0.1.0.dist-info/WHEEL
hello_py_1802-0.1.0.dist-info/top_level.txt
hello_py_1802-0.1.0.dist-info/RECORD
