Metadata-Version: 2.2
Name: hello-py-1802
Version: 0.1.0
Summary: A simple Python package that returns "hello"
Home-page: https://github.com/yourusername/hello-package
Author: Your Name
Author-email: your.email@example.com
Classifier: Programming Language :: Python :: 3
Classifier: License :: OSI Approved :: MIT License
Classifier: Operating System :: OS Independent
Requires-Python: >=3.6
License-File: LICENSE
